ascii_py.py
ascii_python-0.1.0.dist-info/LICENSE
ascii_python-0.1.0.dist-info/METADATA
ascii_python-0.1.0.dist-info/WHEEL
ascii_python-0.1.0.dist-info/top_level.txt
ascii_python-0.1.0.dist-info/RECORD
