Metadata-Version: 2.1
Name: ascii-python
Version: 0.1.0
Summary: A python package for making ascii art
Home-page: https://github.com/Adam-BH/ascii.py
Author: Adam Bhouri
Author-email: adam.bhouri@gmail.com
License: UNKNOWN
Platform: UNKNOWN
Classifier: Programming Language :: Python :: 3
Classifier: Programming Language :: Python :: 3.7
Classifier: License :: OSI Approved :: MIT License
Classifier: Operating System :: OS Independent
Requires-Dist: opencv-python
Provides-Extra: dev
Requires-Dist: wheel ; extra == 'dev'
Requires-Dist: sdist ; extra == 'dev'
